MANIFEST.in
Pipfile
Pipfile.lock
README.md
setup.py
boaviztapi/__init__.py
boaviztapi/main.py
boaviztapi/data/components/cpu_manufacture.csv
boaviztapi/data/components/cpu_power.csv
boaviztapi/data/components/gpu_power.csv
boaviztapi/data/components/ram_manufacture.csv
boaviztapi/data/components/ram_power.csv
boaviztapi/data/components/ssd_manufacture.csv
boaviztapi/data/components/ssd_power.csv
boaviztapi/data/devices/server/dellR740.json
boaviztapi/data/devices/server/high.json
boaviztapi/data/devices/server/low.json
boaviztapi/data/devices/server/medium.json
boaviztapi/data/electricity/usage_impact_factors.csv
boaviztapi/dto/__init__.py
boaviztapi/dto/component_dto.py
boaviztapi/dto/server_dto.py
boaviztapi/model/__init__.py
boaviztapi/model/components/__init__.py
boaviztapi/model/components/component.py
boaviztapi/model/components/usage.py
boaviztapi/model/devices/__init__.py
boaviztapi/model/devices/device.py
boaviztapi/routers/__init__.py
boaviztapi/routers/cloud_router.py
boaviztapi/routers/component_router.py
boaviztapi/routers/server_router.py
boaviztapi/routers/openapi_doc/__init__.py
boaviztapi/routers/openapi_doc/descriptions.py
boaviztapi/routers/openapi_doc/examples.py
boaviztapi/service/__init__.py
boaviztapi/service/archetype.py
boaviztapi/service/bottom_up.py
boaviztapi/service/verbose.py
boaviztapi_test.egg-info/PKG-INFO
boaviztapi_test.egg-info/SOURCES.txt
boaviztapi_test.egg-info/dependency_links.txt
boaviztapi_test.egg-info/entry_points.txt
boaviztapi_test.egg-info/requires.txt
boaviztapi_test.egg-info/top_level.txt