Metadata-Version: 2.1
Name: boaviztapi-test
Version: 0.0.2
Summary: Giving access to BOAVIZTA referenced datas and methodologies trought a RESTful api 
Home-page: https://github.com/Boavizta/Tools-API
License: UNKNOWN
Keywords: boavizta,api
Platform: UNKNOWN
Classifier: Programming Language :: Python :: 3
Classifier: Programming Language :: Python :: 3.7
Classifier: Programming Language :: Python :: 3.8
Classifier: Programming Language :: Python :: 3.9
Classifier: Intended Audience :: Developers
Classifier: Operating System :: OS Independent
Requires-Python: >=3.7
